pyzonevalidator/__init__.py
pyzonevalidator/pyzonevalidator.py
pyzonevalidator-0.3.2.dist-info/WHEEL
pyzonevalidator-0.3.2.dist-info/METADATA
pyzonevalidator-0.3.2.dist-info/RECORD
