Metadata-Version: 2.1
Name: pyzonevalidator
Version: 0.3.2
Summary: Validate DNS Zones programmatically
Home-page: https://github.com/Nextpertise/pyzonevalidator
Author: Teun Ouwehand
Author-email: teun@nextpertise.nl
Requires-Python: >=3.8,<4.0
Classifier: Programming Language :: Python :: 3
Classifier: Programming Language :: Python :: 3.8
Classifier: Programming Language :: Python :: 3.9
Project-URL: Repository, https://github.com/Nextpertise/pyzonevalidator
